fbtftp/__init__.py
fbtftp/base_handler.py
fbtftp/base_server.py
fbtftp/constants.py
fbtftp/netascii.py
fbtftp-0.5.dist-info/AUTHORS
fbtftp-0.5.dist-info/LICENSE
fbtftp-0.5.dist-info/LICENSE-examples
fbtftp-0.5.dist-info/METADATA
fbtftp-0.5.dist-info/WHEEL
fbtftp-0.5.dist-info/top_level.txt
fbtftp-0.5.dist-info/RECORD
