Metadata-Version: 2.1
Name: fbtftp
Version: 0.5
Summary: A python3 framework to build dynamic TFTP servers
Home-page: https://www.github.com/facebook/fbtftp
Author: Angelo Failla
Author-email: pallotron@fb.com
License: BSD
Keywords: tftp daemon infrastructure provisioning netboot
Platform: UNKNOWN
Classifier: Development Status :: 5 - Production/Stable
Classifier: License :: OSI Approved :: MIT License
Classifier: Operating System :: POSIX :: Linux
Classifier: Programming Language :: Python :: 3 :: Only
Classifier: Programming Language :: Python :: 3.5
Classifier: Programming Language :: Python :: 3.6
Classifier: Programming Language :: Python :: 3.7
Classifier: Programming Language :: Python :: 3.8
Classifier: Programming Language :: Python :: 3.9
Classifier: Topic :: Software Development :: Libraries :: Application Frameworks
Classifier: Topic :: System :: Boot
Classifier: Topic :: Utilities
Classifier: Intended Audience :: Developers
License-File: LICENSE
License-File: LICENSE-examples
License-File: AUTHORS
